ScientificPython-2.6.3.dist-info/metadata.json
ScientificPython-2.6.3.dist-info/WHEEL
ScientificPython-2.6.3.dist-info/top_level.txt
ScientificPython-2.6.3.dist-info/DESCRIPTION.rst
ScientificPython-2.6.3.dist-info/METADATA
ScientificPython-2.6.3.dist-info/RECORD
Scientific/_affinitypropagation.cpython-35m-i386-linux-gnu.so
Scientific/Mathematica.py
Scientific/NRNG.py
Scientific/_interpolation.cpython-35m-i386-linux-gnu.so
Scientific/__pkginfo__.py
Scientific/__init__.py
Scientific/N.py
Scientific/_vector.cpython-35m-i386-linux-gnu.so
Scientific/LA.py
Scientific/FFT.py
Scientific/_netcdf.cpython-35m-i386-linux-gnu.so
Scientific/DictWithDefault.py
Scientific/indexing.py
Scientific/NumberDict.py
Scientific/Threading/TaskManager.py
Scientific/Threading/__init__.py
Scientific/IO/PDBExportFilters.py
Scientific/IO/NetCDF.py
Scientific/IO/PDBSpaceGroups.py
Scientific/IO/__init__.py
Scientific/IO/FortranFormat.py
Scientific/IO/TextFile.py
Scientific/IO/ArrayIO.py
Scientific/IO/PDB.py
Scientific/Visualization/VRML2.py
Scientific/Visualization/Color.py
Scientific/Visualization/__init__.py
Scientific/Visualization/PyMOL.py
Scientific/Visualization/VRML.py
Scientific/Visualization/VMD.py
Scientific/Visualization/Chimera.py
Scientific/Visualization/VPython.py
Scientific/Functions/Rational.py
Scientific/Functions/LeastSquares.py
Scientific/Functions/FindRoot.py
Scientific/Functions/__init__.py
Scientific/Functions/Polynomial.py
Scientific/Functions/Romberg.py
Scientific/Functions/Interpolation.py
Scientific/Functions/Derivatives.py
Scientific/Functions/FirstDerivatives.py
Scientific/DistributedComputing/MasterSlave.py
Scientific/DistributedComputing/TaskManager.py
Scientific/DistributedComputing/__init__.py
Scientific/Statistics/__init__.py
Scientific/Statistics/Histogram.py
Scientific/TkWidgets/TkVisualizationCanvas.py
Scientific/TkWidgets/Utility.py
Scientific/TkWidgets/TkPlotCanvas.py
Scientific/TkWidgets/__init__.py
Scientific/MPI/__init__.py
Scientific/MPI/IO.py
Scientific/MPI/core.py
Scientific/Physics/Potential.py
Scientific/Physics/PhysicalQuantities.py
Scientific/Physics/__init__.py
Scientific/.libs/libsz-efee47d6.so.2.0.1
Scientific/.libs/libhdf5-74528fd1.so.10.2.1
