Metadata-Version: 2.0
Name: ScientificPython
Version: 2.6.3
Summary: Various Python modules for scientific computing
Home-page: http://dirac.cnrs-orleans.fr/ScientificPython/
Author: Konrad Hinsen
Author-email: hinsen@cnrs-orleans.fr
License: CeCILL-C
Platform: UNKNOWN
Requires-Dist: numpy (>=1.6)
Requires-Dist: oldnumeric
Requires-Dist: six
